logcabin/__init__.py
logcabin/talc.py
log_cabin_client-0.0.1.dist-info/LICENSE
log_cabin_client-0.0.1.dist-info/METADATA
log_cabin_client-0.0.1.dist-info/WHEEL
log_cabin_client-0.0.1.dist-info/top_level.txt
log_cabin_client-0.0.1.dist-info/RECORD
