Metadata-Version: 2.1
Name: log-cabin-client
Version: 0.0.1
Summary: Logging client for LogCabin
Author-email: Max Kerr <max@joinhomey.co>
Classifier: Programming Language :: Python :: 3
Classifier: License :: Other/Proprietary License
Classifier: Operating System :: OS Independent
Requires-Python: >=3.7
License-File: LICENSE
Requires-Dist: supabase (>=1.0.3)
Requires-Dist: openai (>=0.11.6)
